simplepokedex/LICENSE
simplepokedex/README.md
simplepokedex/generatePokemon.py
simplepokedex/lookup.py
simplepokedex/pokedex.py
simplepokedex/poketypes.py
simplepokedex/tests/abilityLookup_test.py
simplepokedex/tests/generatePokemon_test.py
simplepokedex/tests/pokemonLookup_test.py
simplepokedex/tests/poketypes_test.py
simplepokedex-1.0.3.dist-info/METADATA
simplepokedex-1.0.3.dist-info/WHEEL
simplepokedex-1.0.3.dist-info/top_level.txt
simplepokedex-1.0.3.dist-info/RECORD
