Metadata-Version: 2.1
Name: simplepokedex
Version: 1.0.3
Summary: Simple Pokedex Package
Author: Eric Lin, Alice Ding, Justin Zhao
License: GNU GENERAL PUBLIC LICENSE
